nlp_data_py/__init__.py
nlp_data_py/commons/__init__.py
nlp_data_py/commons/bookdef.py
nlp_data_py/commons/splitter.py
nlp_data_py/commons/utils/__init__.py
nlp_data_py/commons/utils/fileutils.py
nlp_data_py/commons/utils/helpers.py
nlp_data_py/commons/utils/logging.py
nlp_data_py/dataset/__init__.py
nlp_data_py/dataset/command_line.py
nlp_data_py/dataset/constants.py
nlp_data_py/dataset/dataset.py
nlp_data_py/dataset/wiki.py
nlp_data_py/tests/__init__.py
nlp_data_py/tests/test_bookdef.py
nlp_data_py/tests/test_dataset.py
nlp_data_py/tests/test_fileutils.py
nlp_data_py/tests/test_helpers.py
nlp_data_py/tests/test_splitter.py
nlp_data_py/tests/test_wiki.py
nlp_data_py-0.0.9.dist-info/LICENSE
nlp_data_py-0.0.9.dist-info/METADATA
nlp_data_py-0.0.9.dist-info/WHEEL
nlp_data_py-0.0.9.dist-info/entry_points.txt
nlp_data_py-0.0.9.dist-info/top_level.txt
nlp_data_py-0.0.9.dist-info/RECORD
