Metadata-Version: 2.1
Name: nlp-data-py
Version: 0.0.9
Summary: Create Test, Train and Validation datasets for NLP. Currently, creating these datasets from wikipedia is supported
Home-page: https://github.com/madutv/nlp-data-py.git
Author: Madhu TV
Author-email: madhavi.tv@gmail.com
License: UNKNOWN
Platform: UNKNOWN
Classifier: Programming Language :: Python :: 3
Classifier: License :: OSI Approved :: MIT License
Classifier: Operating System :: OS Independent
Requires-Dist: numpy
Requires-Dist: wikipedia
